README.md
diceparser.py
grammar.lark
main.py
docs/features.md
docs/index.md
docs/usage.md
helpers/__init__.py
helpers/groups.py
diceparse-1.0.8.dist-info/METADATA
diceparse-1.0.8.dist-info/WHEEL
diceparse-1.0.8.dist-info/licenses/LICENSE
diceparse-1.0.8.dist-info/RECORD
