Metadata-Version: 2.4
Name: diceparse
Version: 1.0.8
Summary: A dice rolling parser with a surprising number of features.
Project-URL: Homepage, https://dice.jamesthebard.net
Author: JamesTheBard
License-Expression: GPL-3.0-or-later
License-File: LICENSE
Requires-Python: >=3.11
Requires-Dist: lark>=1.2.2
